k8s_sandbox/__init__.py
k8s_sandbox/_helm.py
k8s_sandbox/_kubernetes_api.py
k8s_sandbox/_logger.py
k8s_sandbox/_manager.py
k8s_sandbox/_prereqs.py
k8s_sandbox/_sandbox_environment.py
k8s_sandbox/py.typed
k8s_sandbox/_pod/__init__.py
k8s_sandbox/_pod/buffer.py
k8s_sandbox/_pod/error.py
k8s_sandbox/_pod/execute.py
k8s_sandbox/_pod/executor.py
k8s_sandbox/_pod/get_returncode.py
k8s_sandbox/_pod/op.py
k8s_sandbox/_pod/pod.py
k8s_sandbox/_pod/read.py
k8s_sandbox/_pod/write.py
k8s_sandbox/compose/__init__.py
k8s_sandbox/compose/_compose.py
k8s_sandbox/compose/_converter.py
k8s_sandbox/resources/compose/README.md
k8s_sandbox/resources/compose/compose-spec.json
k8s_sandbox/resources/helm/agent-env/Chart.yaml
k8s_sandbox/resources/helm/agent-env/README.md
k8s_sandbox/resources/helm/agent-env/generate-docs.md
k8s_sandbox/resources/helm/agent-env/values.schema.json
k8s_sandbox/resources/helm/agent-env/values.yaml
k8s_sandbox/resources/helm/agent-env/templates/additional-resources.yaml
k8s_sandbox/resources/helm/agent-env/templates/coredns.yaml
k8s_sandbox/resources/helm/agent-env/templates/network-policy.yaml
k8s_sandbox/resources/helm/agent-env/templates/pvc.yaml
k8s_sandbox/resources/helm/agent-env/templates/services.yaml
k8s_sandbox/resources/helm/agent-env/templates/helpers/_helpers.tpl
inspect_k8s_sandbox-0.3.0.dist-info/METADATA
inspect_k8s_sandbox-0.3.0.dist-info/WHEEL
inspect_k8s_sandbox-0.3.0.dist-info/entry_points.txt
inspect_k8s_sandbox-0.3.0.dist-info/licenses/LICENSE
inspect_k8s_sandbox-0.3.0.dist-info/RECORD
