Metadata-Version: 2.4
Name: inspect-k8s-sandbox
Version: 0.3.0
Summary: A Kubernetes Sandbox Environment for Inspect
Author: UK AI Security Institute
License-File: LICENSE
Requires-Python: >=3.10
Requires-Dist: inspect-ai>=0.3.120
Requires-Dist: jsonschema>=4.23.0
Requires-Dist: kubernetes>=31.0.0
Provides-Extra: dev
Requires-Dist: mypy>=1.9.0; extra == 'dev'
Requires-Dist: pre-commit>=3.6.2; extra == 'dev'
Requires-Dist: pytest-asyncio>=0.23.7; extra == 'dev'
Requires-Dist: pytest-env>=1.2.0; extra == 'dev'
Requires-Dist: pytest-repeat>=0.9.3; extra == 'dev'
Requires-Dist: pytest>=8.1.1; extra == 'dev'
Requires-Dist: ruff>=0.9.6; extra == 'dev'
Requires-Dist: types-jsonschema>=4.23.0.20241208; extra == 'dev'
Requires-Dist: types-pyyaml>=6.0.12; extra == 'dev'
